sr.comp-1.12.0-py3.11-nspkg.pth
sr/comp/arenas.py
sr/comp/comp.py
sr/comp/match_period.py
sr/comp/match_period_clock.py
sr/comp/matches.py
sr/comp/py.typed
sr/comp/ranker.py
sr/comp/raw_compstate.py
sr/comp/scores.py
sr/comp/teams.py
sr/comp/types.py
sr/comp/validation.py
sr/comp/venue.py
sr/comp/winners.py
sr/comp/yaml_loader.py
sr/comp/knockout_scheduler/__init__.py
sr/comp/knockout_scheduler/automatic_scheduler.py
sr/comp/knockout_scheduler/base_scheduler.py
sr/comp/knockout_scheduler/seeding.py
sr/comp/knockout_scheduler/stable_random.py
sr/comp/knockout_scheduler/static_scheduler.py
sr.comp-1.12.0.dist-info/AUTHORS.rst
sr.comp-1.12.0.dist-info/LICENSE
sr.comp-1.12.0.dist-info/METADATA
sr.comp-1.12.0.dist-info/WHEEL
sr.comp-1.12.0.dist-info/namespace_packages.txt
sr.comp-1.12.0.dist-info/top_level.txt
sr.comp-1.12.0.dist-info/zip-safe
sr.comp-1.12.0.dist-info/RECORD
