Metadata-Version: 2.1
Name: sr.comp
Version: 1.12.0
Summary: Reliable software for running robotics competitions
Home-page: https://github.com/PeterJCLaw/srcomp/wiki
Author: Student Robotics Competition Software SIG
Author-email: srobo-devel@googlegroups.com
Project-URL: Documentation, https://srcomp.readthedocs.org/
Project-URL: Code, https://github.com/PeterJCLaw/srcomp
Project-URL: Issue tracker, https://github.com/PeterJCLaw/srcomp/issues
Classifier: Intended Audience :: Developers
Classifier: License :: OSI Approved :: GNU General Public License v3 (GPLv3)
Classifier: Operating System :: OS Independent
Classifier: Programming Language :: Python :: 3
Classifier: Programming Language :: Python :: 3.9
Classifier: Programming Language :: Python :: 3.10
Classifier: Programming Language :: Python :: 3.11
Classifier: Programming Language :: Python :: 3.12
Classifier: Programming Language :: Python :: 3.13
Classifier: Programming Language :: Python :: 3 :: Only
Classifier: Topic :: Software Development :: Libraries
Requires-Python: >=3.9
License-File: LICENSE
License-File: AUTHORS.rst
Requires-Dist: PyYAML<7,>=5.1.2
Requires-Dist: league-ranker<2,>=0.1
Requires-Dist: python-dateutil<3,>=2.7
Requires-Dist: typing-extensions<5,>=4
